{
    "users":[
       {
        "name":"grufkork",
        "password":"SocketGame88!",
		"admin":true
    },
    {
        "name":"khaled",
        "password":"spelaspel",
		"admin":false
    },
    {
        "name":"xtella",
        "password":"KisseKatt05!",
		"admin":false
    },
	{
	    "name":"musis",
	    "password":"leverpastej",
		"admin":false
	},
	{
	    "name":"jeprin",
	    "password":"jesper44",
		"admin":false
	},
	{
	    "name":"fusklapp3",
	    "password":"burk",
		"admin":false
	},
	{
	    "name":"bennablixten",
	    "password":"rumpa",
		"admin":false
	},
	{
	    "name":"camis5",
	    "password":"nej",
		"admin":false
	},
	{
		"name":"clutchcontrol",
		"password":"blamblam",
		"admin":false
	},
	{
		"name":"pengiboz",
		"password":"shaxing",
		"admin":false
	},
	{
		"name":"pierre",
		"password":"IsTheBest",
		"admin":false
	},
	{
		"name":"gurkmeja1337",
		"password":"lösenord",
		"admin":false
	},
	{
		"name":"roxiethecat",
		"password":"roxie111",
		"admin":false
	},
	{
		"name":"neilfeim",
		"password":"Yxa123",
		"admin":false
	},
	{
		"name":"eddie",
		"password":"Ek7",
		"admin":false
	},
	{
		"name":"funck",
		"password":"fuck",
		"admin":false
	},
	{
		"name":"erkoperki",
		"password":"Kunskap123",
		"admin":false
	},
	{
		"name":"lullegamingid",
		"password":"hallberg",
		"admin":false
	},
	{
		"name":"lnt",
		"password":"lnt123m",
		"admin":false
	},
	{
		"name":"hoppa",
		"password":"hallå",
		"admin":false
	},
	{
		"name":"skallepär",
		"password":"senap",
		"admin":false
	},
	{
		"name":"leopold",
		"password":"leopold15",
		"admin":false
	},
	{
		"name":"addenor",
		"password":"Adam6928",
		"admin":false
	},
	{
		"name":"thorin",
		"password":"griffinkung123",
		"admin":false
	},
	{
		"name":"thorinek",
		"password":"erikärnoob",
		"admin":false
	},
	{
		"name":"jurmungandur",
		"password":"troja",
		"admin":false
	},
	{
		"name":"xxander",
		"password":"BigGuns",
		"admin":false
	},
	{
		"name":"hannes",
		"password":"lol",
		"admin":false
	},
	{
		"name":"lau",
		"password":"tåg",
		"admin":false
	},
	{
		"name":"lau",
		"password":"tåg",
		"admin":false
	},
	{
		"name":"anii",
		"password":"Anii1234",
		"admin":false
	},
	{
		"name":"rosaflickan",
		"password":"amanda123",
		"admin":false
	},
	{
		"name":"sigge",
		"password":"so9",
		"admin":false
	}
    ]
}